{
  "name": "Category",
  "path": "/*",
  "sections": {
    "variants": [
      {
        "rule": {
          "__resolveType": "website/matchers/always.ts"
        },
        "value": [
          {
            "__resolveType": "Header - 02"
          },
          {
            "__resolveType": "site/sections/Category/BrandBanner.tsx",
            "matcherSections": [
              {
                "image": {
                  "desktop": "https://deco-sites-assets.s3.sa-east-1.amazonaws.com/meiasola/b2a86b8e-7f7b-41e1-8e9e-8498d8945769/azz.png",
                  "mobile": "https://deco-sites-assets.s3.sa-east-1.amazonaws.com/meiasola/b2c8fc09-d2e2-4f4e-b3fc-80a92f2918d1/15.png"
                },
                "label": "/arezzo?map=brand"
              },
              {
                "image": {
                  "desktop": "https://deco-sites-assets.s3.sa-east-1.amazonaws.com/meiasola/f41a128e-5995-4574-9c3e-2c62d517bc4b/anacapri.png",
                  "mobile": "https://deco-sites-assets.s3.sa-east-1.amazonaws.com/meiasola/f1b4392d-4102-4e0c-b0e5-b935da34e624/16.png"
                },
                "label": "/anacapri?map=brand"
              },
              {
                "image": {
                  "desktop": "https://deco-sites-assets.s3.sa-east-1.amazonaws.com/meiasola/7aa48451-ace6-4065-a0a8-722e26a0e978/birman.png",
                  "mobile": "https://deco-sites-assets.s3.sa-east-1.amazonaws.com/meiasola/263dc8d1-e2ff-4a5c-86ff-f089ecccb1db/13.png"
                },
                "label": "/alexandre-birman?map=brand"
              }
            ]
          },
          {
            "__resolveType": "site/sections/Product/SearchResult.tsx",
            "page": {
              "data": {
                "sort": "release:desc",
                "count": 24,
                "fuzzy": "automatic",
                "__resolveType": "vtex/loaders/intelligentSearch/productListingPage.ts",
                "selectedFacets": [],
                "hideUnavailableItems": true
              },
              "extensions": [
                {
                  "__resolveType": "site/loaders/meiasola/extensionProductListingPage.ts"
                }
              ],
              "__resolveType": "commerce/loaders/product/productListingPage.ts"
            },
            "sizes": {
              "sizes": [
                {
                  "label": "33"
                },
                {
                  "label": "34"
                },
                {
                  "label": "35"
                },
                {
                  "label": "36"
                },
                {
                  "label": "37"
                },
                {
                  "label": "38"
                },
                {
                  "label": "39"
                },
                {
                  "label": "40"
                }
              ],
              "title": "ESCOLHA SUA NUMERAÇÃO",
              "routesToShow": [
                {
                  "label": "/sapatos"
                },
                {
                  "label": "/sale"
                }
              ]
            },
            "images": [
              {
                "alt": "Imagem de um sapato salto alto",
                "src": "https://deco-sites-assets.s3.sa-east-1.amazonaws.com/meiasola/fda8865f-3f34-424d-8b2f-5536e56068a7/4.png",
                "route": "/sapatos",
                "srcMobile": "https://deco-sites-assets.s3.sa-east-1.amazonaws.com/meiasola/70064829-e857-42c9-a1bd-fe013e06ce34/4.png"
              },
              {
                "alt": "Imagem de bolsas",
                "src": "https://deco-sites-assets.s3.sa-east-1.amazonaws.com/meiasola/85e90d32-fd39-4d4a-ad76-18e0be038db3/UTILIZE-O-CUPOM-LIVELO-E-GANHE-5-PONTOS-PARA-CLUBE-E-4-PONTOS-PARA-NAO-CLUBE-A-CADA-1-REAL-GASTO.png",
                "route": "/bolsas",
                "srcMobile": "https://deco-sites-assets.s3.sa-east-1.amazonaws.com/meiasola/d4f403d2-1534-4af5-a916-fb8c12a75c70/categoria-mobile.png"
              },
              {
                "alt": "Imagem de pulseira dourada",
                "src": "https://deco-sites-assets.s3.sa-east-1.amazonaws.com/meiasola/de1cc87b-8cea-436c-9e4e-6330dd912415/6.png",
                "route": "/acessorios",
                "srcMobile": "https://deco-sites-assets.s3.sa-east-1.amazonaws.com/meiasola/490074b0-3e1c-4987-aa8e-17bf204428b2/6.png"
              },
              {
                "alt": "Imagem de Sandálias ",
                "src": "https://deco-sites-assets.s3.sa-east-1.amazonaws.com/meiasola/6a65bbde-21d2-458d-8b25-9b390df91ab1/3.png",
                "route": "/sapatos/sandalia",
                "srcMobile": "https://deco-sites-assets.s3.sa-east-1.amazonaws.com/meiasola/fdce21e8-4c83-43ad-b713-d28b23297ddf/3.png"
              }
            ],
            "notFoundPage": {
              "data": {
                "sort": "price:desc",
                "count": 24,
                "fuzzy": "automatic",
                "__resolveType": "vtex/loaders/intelligentSearch/productListingPage.ts",
                "selectedFacets": [
                  {
                    "key": "productClusterIds",
                    "value": "151"
                  }
                ]
              },
              "extensions": [
                {
                  "__resolveType": "site/loaders/meiasola/extensionProductListingPage.ts"
                }
              ],
              "__resolveType": "commerce/loaders/product/productListingPage.ts"
            }
          },
          {
            "__resolveType": "site/sections/Category/CategoryTextReadMore.tsx",
            "matcherSections": [
              {
                "text": "<p class=\"MsoNormal\"><span style=\"font-size: 10pt;\" data-mce-style=\"font-size: 10pt;\"><strong>Bolsa Feminina Grande:&nbsp;</strong></span></p><p class=\"MsoNormal\"><span style=\"font-size: 10pt;\" data-mce-style=\"font-size: 10pt;\">A bolsa grande feminina é um acessório que une funcionalidade e estilo em uma única peça. Na Meia Sola, você encontra uma ampla variedade de bolsas em matelassê estampa animal. Aprimore seu look com praticidade e elegância.</span></p><p class=\"MsoNormal\"><span style=\"font-size: 10pt;\" data-mce-style=\"font-size: 10pt;\"><strong>Bolsa Feminina Média</strong>: </span></p><p class=\"MsoNormal\"><span style=\"font-size: 10pt;\" data-mce-style=\"font-size: 10pt;\">Em um equilíbrio ideal entre praticidade e elegância, as bolsas de tamanho médio trazem as últimas tendências da moda diretamente para o seu guarda-roupa, com designs, cores e materiais que acrescentam sofisticação a qualquer look. Adquira já a sua bolsa e arrase no visual!</span></p><p class=\"MsoNormal\"><span style=\"font-size: 10pt;\" data-mce-style=\"font-size: 10pt;\"><strong>Bolsa Feminina Pequena</strong>: </span></p><p class=\"MsoNormal\"><span style=\"font-size: 10pt;\" data-mce-style=\"font-size: 10pt;\">Explore a nossa seleção de bolsas pequenas e encontre o modelo ideal para complementar o seu look. Com opções em couro, tecido, e outros materiais, oferecemos uma variedade de escolhas para atender a todos os estilos e gostos. Garanta já a sua bolsa pequena e adicione um toque de sofisticação e modernidade às suas produções. Aproveite o frete grátis e parcelamento em até 10x. Compre agora!</span></p><p class=\"MsoNormal\"><span style=\"font-size: 10pt;\" data-mce-style=\"font-size: 10pt;\"><strong>Bolsa Tote Feminina</strong>: <span style=\"mso-spacerun: yes;\" data-mce-style=\"mso-spacerun: yes;\">&nbsp;</span></span></p><p class=\"MsoNormal\"><span style=\"font-size: 10pt;\" data-mce-style=\"font-size: 10pt;\">Bolsa tote é a escolha perfeita para a mulher contemporânea que está sempre em movimento, seja no trabalho ou em eventos formais. Com um toque de sofisticação e originalidade, ela adiciona um toque de ousadia a qualquer look.</span></p><p class=\"MsoNormal\"><span style=\"font-size: 10pt;\" data-mce-style=\"font-size: 10pt;\">Cada coleção é cuidadosamente elaborada para criar peças marcantes, cheias de estilo e que se mantêm icônicas ao longo dos anos. Explore nossa variedade de bolsas tote e garanta a sua agora!</span></p><p class=\"MsoNormal\"><span style=\"font-size: 10pt;\" data-mce-style=\"font-size: 10pt;\"><strong>Bolsa Tiracolo Feminina</strong>: </span></p><p class=\"MsoNormal\"><span style=\"font-size: 10pt;\" data-mce-style=\"font-size: 10pt;\">A bolsa tiracolo com mais glamour, mantendo sua praticidade e conforto. Com design elegante e autêntico, ela é essencial para looks deslumbrantes que vão te fazer se destacar.</span></p><p class=\"MsoNormal\"><span style=\"font-size: 10pt;\" data-mce-style=\"font-size: 10pt;\">Não se limite à tradicional bolsa tiracolo preta. Temos opções metalizadas, com correntes e formatos divertidos que capturam o estilo urban chic da cidade. Seja arrojada e esteja sempre em destaque!</span></p><p class=\"MsoNormal\"><span style=\"font-size: 10pt;\" data-mce-style=\"font-size: 10pt;\"><strong>Bolsa shopping Feminina</strong>: </span></p><p class=\"MsoNormal\"><span style=\"font-size: 10pt;\" data-mce-style=\"font-size: 10pt;\">A bolsa shopping não é apenas uma tendência, é a escolha ideal para quem vive uma vida agitada. Com um design contemporâneo, sofisticado e versátil, ela permite que você esteja preparada para qualquer situação sem trocar de bolsa.</span></p><p class=\"MsoNormal\"><span style=\"font-size: 10pt;\" data-mce-style=\"font-size: 10pt;\">Seja para um encontro casual ou um compromisso de trabalho, a bolsa shopping reflete a essência ousada, moderna e cativante que todas as mulheres possuem. Confira as opções e entre na tendência!</span></p><p class=\"MsoNormal\"><span style=\"font-size: 10pt;\" data-mce-style=\"font-size: 10pt;\"><strong>Pochete Feminina</strong>: </span></p><p class=\"MsoNormal\"><span style=\"font-size: 10pt;\" data-mce-style=\"font-size: 10pt;\">A pochete, tão querida nos festivais, é um item essencial para as fashionistas que valorizam funcionalidade, conforto e estilo. Disponíveis em diversas cores, formatos e texturas. Combine a sua pochete com uma jaqueta puffer, meia calça-arrastão e correntes para brilhar em todos os eventos. É a combinação perfeita para um look cheio de personalidade e estilo!</span></p><p class=\"MsoNormal\"><span style=\"font-size: 10pt;\" data-mce-style=\"font-size: 10pt;\"><strong><span style=\"vertical-align: inherit;\" data-mce-style=\"vertical-align: inherit;\"><span style=\"vertical-align: inherit;\" data-mce-style=\"vertical-align: inherit;\">Bolsa de embreagem</span></span></strong><span style=\"vertical-align: inherit;\" data-mce-style=\"vertical-align: inherit;\"><span style=\"vertical-align: inherit;\" data-mce-style=\"vertical-align: inherit;\"> :</span></span></span></p><p class=\"MsoNormal\"><span style=\"font-size: 10pt;\" data-mce-style=\"font-size: 10pt;\">Você já conhece nossas clutches é o toque de sofisticação que toda mulher poderosa e antenada em moda precisa ter em seu guarda-roupa. Do casual ao formal, ela eleva qualquer look, transformando momentos simples em memórias inesquecíveis.</span></p><p class=\"MsoNormal\"><span style=\"font-size: 10pt;\" data-mce-style=\"font-size: 10pt;\">Disponíveis em couro, metal e strass, as clutches chegam em diversas cores e formatos para você combinar com o seu estilo do dia.</span></p><p class=\"MsoNormal\"><span style=\"font-size: 10pt;\" data-mce-style=\"font-size: 10pt;\"><strong>Mala e mochila Feminina</strong>: </span></p><p class=\"MsoNormal\"><span style=\"font-size: 10pt;\" data-mce-style=\"font-size: 10pt;\">Se você está em busca de bolsas estilosas para arrasar no look de viagem, não precisa mais procurar. Nossa seleção exclusiva de malas e mochilas une praticidade, organização e tendência em modelos super estilosos.</span></p><p class=\"MsoNormal\"><span style=\"font-size: 10pt;\" data-mce-style=\"font-size: 10pt;\">Das malas de mão às de rodinha, todas possuem o tamanho ideal para serem levadas na cabine do avião, garantindo que você tenha tudo o que precisa consigo. Explore nossos modelos, escolha o look perfeito e divirta-se.</span></p><p class=\"MsoNormal\"><br data-mce-bogus=\"1\"></p>",
                "image": {
                  "alt": "Tendência em bolsas femininas",
                  "width": 531,
                  "height": 484,
                  "source": "https://deco-sites-assets.s3.sa-east-1.amazonaws.com/meiasola/28661701-192a-4231-899a-92499d485ad1/resized_image.png"
                },
                "label": "/bolsas",
                "title": "Tendência em bolsas femininas que trazem autenticidade!",
                "maxCharacters": 870
              }
            ]
          },
          {
            "__resolveType": "Footer - 01"
          },
          {
            "__resolveType": "commerce/sections/Seo/SeoPLP.tsx",
            "type": "website",
            "jsonLD": {
              "sort": "release:desc",
              "count": 24,
              "fuzzy": "automatic",
              "__resolveType": "vtex/loaders/intelligentSearch/productListingPage.ts",
              "selectedFacets": [],
              "hideUnavailableItems": true
            },
            "titleTemplate": "%s",
            "descriptionTemplate": "%s"
          },
          {
            "__resolveType": "Analytics - GTM-NJRC6Q2"
          }
        ]
      }
    ],
    "__resolveType": "website/flags/multivariate.ts"
  },
  "__resolveType": "website/pages/Page.tsx"
}